{"H": 612, "detections": [{"class_str": "person", "score": 1.0, "class_no": 1, "box_coords": [0.305, 0.0, 0.981, 0.377]}, {"class_str": "person", "score": 0.999, "class_no": 1, "box_coords": [0.306, 0.498, 0.988, 0.998]}, {"class_str": "person", "score": 0.998, "class_no": 1, "box_coords": [0.143, 0.697, 0.244, 0.726]}, {"class_str": "person", "score": 0.996, "class_no": 1, "box_coords": [0.134, 0.671, 0.245, 0.701]}, {"class_str": "person", "score": 0.268, "class_no": 1, "box_coords": [0.043, 0.513, 0.138, 0.555]}, {"class_str": "person", "score": 0.109, "class_no": 1, "box_coords": [0.058, 0.541, 0.138, 0.565]}, {"class_str": "person", "score": 0.674, "class_no": 1, "box_coords": [0.137, 0.689, 0.244, 0.714]}, {"class_str": "person", "score": 0.061, "class_no": 1, "box_coords": [0.165, 0.001, 0.255, 0.019]}, {"class_str": "person", "score": 0.055, "class_no": 1, "box_coords": [0.042, 0.521, 0.109, 0.55]}, {"class_str": "car", "score": 0.775, "class_no": 3, "box_coords": [0.158, 0.821, 0.186, 0.861]}, {"class_str": "car", "score": 0.051, "class_no": 3, "box_coords": [0.151, 0.004, 0.162, 0.035]}, {"class_str": "handbag", "score": 0.053, "class_no": 27, "box_coords": [0.902, 0.011, 0.992, 0.241]}, {"class_str": "skateboard", "score": 0.186, "class_no": 37, "box_coords": [0.236, 0.694, 0.247, 0.715]}, {"class_str": "skateboard", "score": 0.054, "class_no": 37, "box_coords": [0.233, 0.688, 0.245, 0.711]}, {"class_str": "skateboard", "score": 0.07, "class_no": 37, "box_coords": [0.244, 0.696, 0.25, 0.717]}, {"class_str": "skateboard", "score": 0.051, "class_no": 37, "box_coords": [0.238, 0.689, 0.247, 0.73]}, {"class_str": "sandwich", "score": 0.244, "class_no": 49, "box_coords": [0.532, 0.241, 0.591, 0.339]}, {"class_str": "sandwich", "score": 0.144, "class_no": 49, "box_coords": [0.536, 0.242, 0.582, 0.275]}, {"class_str": "sandwich", "score": 0.281, "class_no": 49, "box_coords": [0.533, 0.237, 0.743, 0.334]}, {"class_str": "sandwich", "score": 0.441, "class_no": 49, "box_coords": [0.877, 0.745, 0.987, 0.858]}, {"class_str": "hot dog", "score": 0.909, "class_no": 53, "box_coords": [0.527, 0.246, 0.735, 0.336]}, {"class_str": "hot dog", "score": 0.462, "class_no": 53, "box_coords": [0.533, 0.243, 0.591, 0.335]}, {"class_str": "hot dog", "score": 0.164, "class_no": 53, "box_coords": [0.534, 0.246, 0.579, 0.274]}, {"class_str": "hot dog", "score": 0.133, "class_no": 53, "box_coords": [0.521, 0.166, 0.737, 0.329]}, {"class_str": "hot dog", "score": 0.756, "class_no": 53, "box_coords": [0.875, 0.738, 0.981, 0.86]}], "image_name": "COCO_train2014_000000085413.jpg", "W": 612}