{"H": 480, "detections": [{"class_str": "person", "score": 0.855, "class_no": 1, "box_coords": [0.426, 0.246, 0.632, 0.542]}, {"class_str": "person", "score": 0.306, "class_no": 1, "box_coords": [0.37, 0.321, 0.627, 0.738]}, {"class_str": "person", "score": 0.69, "class_no": 1, "box_coords": [0.44, 0.21, 0.626, 0.394]}, {"class_str": "person", "score": 0.284, "class_no": 1, "box_coords": [0.432, 0.285, 0.542, 0.388]}, {"class_str": "person", "score": 0.913, "class_no": 1, "box_coords": [0.384, 0.382, 0.67, 0.944]}, {"class_str": "bench", "score": 0.063, "class_no": 14, "box_coords": [0.517, 0.208, 0.954, 0.994]}, {"class_str": "bench", "score": 0.636, "class_no": 14, "box_coords": [0.709, 0.412, 0.979, 0.982]}, {"class_str": "bench", "score": 0.063, "class_no": 14, "box_coords": [0.532, 0.0, 0.993, 0.094]}, {"class_str": "dog", "score": 0.999, "class_no": 17, "box_coords": [0.476, 0.455, 0.66, 0.591]}, {"class_str": "dog", "score": 0.835, "class_no": 17, "box_coords": [0.425, 0.396, 0.649, 0.602]}, {"class_str": "dog", "score": 0.079, "class_no": 17, "box_coords": [0.397, 0.279, 0.627, 0.636]}, {"class_str": "dog", "score": 0.946, "class_no": 17, "box_coords": [0.364, 0.434, 0.453, 0.615]}, {"class_str": "dog", "score": 0.23, "class_no": 17, "box_coords": [0.402, 0.344, 0.646, 0.828]}, {"class_str": "dog", "score": 0.964, "class_no": 17, "box_coords": [0.475, 0.661, 0.539, 0.735]}, {"class_str": "dog", "score": 0.423, "class_no": 17, "box_coords": [0.373, 0.381, 0.475, 0.585]}, {"class_str": "dog", "score": 0.213, "class_no": 17, "box_coords": [0.412, 0.342, 0.616, 0.534]}, {"class_str": "dog", "score": 0.076, "class_no": 17, "box_coords": [0.442, 0.536, 0.584, 0.753]}, {"class_str": "dog", "score": 0.123, "class_no": 17, "box_coords": [0.383, 0.385, 0.548, 0.542]}, {"class_str": "dog", "score": 0.351, "class_no": 17, "box_coords": [0.403, 0.445, 0.659, 0.69]}, {"class_str": "dog", "score": 0.062, "class_no": 17, "box_coords": [0.459, 0.609, 0.555, 0.749]}, {"class_str": "dog", "score": 0.096, "class_no": 17, "box_coords": [0.367, 0.432, 0.457, 0.519]}, {"class_str": "chair", "score": 0.16, "class_no": 57, "box_coords": [0.745, 0.434, 0.985, 0.986]}, {"class_str": "chair", "score": 0.102, "class_no": 57, "box_coords": [0.649, 0.113, 0.997, 0.534]}, {"class_str": "chair", "score": 0.083, "class_no": 57, "box_coords": [0.483, 0.003, 0.984, 0.242]}, {"class_str": "chair", "score": 0.077, "class_no": 57, "box_coords": [0.434, 0.146, 0.991, 0.613]}, {"class_str": "chair", "score": 0.661, "class_no": 57, "box_coords": [0.527, 0.0, 0.992, 0.094]}, {"class_str": "couch", "score": 0.638, "class_no": 58, "box_coords": [0.398, 0.164, 0.883, 0.994]}, {"class_str": "couch", "score": 0.242, "class_no": 58, "box_coords": [0.421, 0.564, 0.643, 0.976]}, {"class_str": "couch", "score": 0.05, "class_no": 58, "box_coords": [0.424, 0.342, 0.477, 0.405]}, {"class_str": "potted plant", "score": 0.452, "class_no": 59, "box_coords": [0.315, 0.11, 0.381, 0.217]}, {"class_str": "potted plant", "score": 0.1, "class_no": 59, "box_coords": [0.321, 0.159, 0.374, 0.221]}, {"class_str": "bed", "score": 0.621, "class_no": 60, "box_coords": [0.411, 0.168, 0.951, 0.999]}, {"class_str": "bed", "score": 0.368, "class_no": 60, "box_coords": [0.562, 0.256, 0.823, 0.993]}, {"class_str": "bed", "score": 0.055, "class_no": 60, "box_coords": [0.598, 0.197, 0.703, 0.555]}, {"class_str": "bed", "score": 0.118, "class_no": 60, "box_coords": [0.618, 0.332, 0.954, 0.999]}, {"class_str": "dining table", "score": 0.847, "class_no": 61, "box_coords": [0.643, 0.16, 0.985, 0.965]}, {"class_str": "dining table", "score": 0.737, "class_no": 61, "box_coords": [0.682, 0.134, 0.999, 0.601]}, {"class_str": "dining table", "score": 0.056, "class_no": 61, "box_coords": [0.756, 0.356, 0.974, 0.966]}, {"class_str": "book", "score": 0.828, "class_no": 74, "box_coords": [0.039, 0.348, 0.12, 0.361]}, {"class_str": "book", "score": 0.603, "class_no": 74, "box_coords": [0.045, 0.363, 0.126, 0.372]}, {"class_str": "book", "score": 0.478, "class_no": 74, "box_coords": [0.046, 0.368, 0.128, 0.377]}, {"class_str": "book", "score": 0.213, "class_no": 74, "box_coords": [0.041, 0.356, 0.124, 0.365]}, {"class_str": "book", "score": 0.678, "class_no": 74, "box_coords": [0.047, 0.372, 0.129, 0.382]}, {"class_str": "book", "score": 0.573, "class_no": 74, "box_coords": [0.053, 0.388, 0.138, 0.401]}, {"class_str": "book", "score": 0.661, "class_no": 74, "box_coords": [0.035, 0.336, 0.119, 0.355]}, {"class_str": "book", "score": 0.581, "class_no": 74, "box_coords": [0.049, 0.378, 0.131, 0.386]}, {"class_str": "book", "score": 0.309, "class_no": 74, "box_coords": [0.052, 0.384, 0.134, 0.393]}, {"class_str": "book", "score": 0.705, "class_no": 74, "box_coords": [0.047, 0.317, 0.114, 0.338]}, {"class_str": "book", "score": 0.722, "class_no": 74, "box_coords": [0.038, 0.297, 0.113, 0.341]}, {"class_str": "book", "score": 0.496, "class_no": 74, "box_coords": [0.034, 0.328, 0.117, 0.345]}, {"class_str": "book", "score": 0.357, "class_no": 74, "box_coords": [0.044, 0.359, 0.131, 0.397]}, {"class_str": "book", "score": 0.131, "class_no": 74, "box_coords": [0.365, 0.086, 0.392, 0.235]}, {"class_str": "book", "score": 0.398, "class_no": 74, "box_coords": [0.035, 0.312, 0.117, 0.356]}, {"class_str": "book", "score": 0.772, "class_no": 74, "box_coords": [0.061, 0.299, 0.108, 0.323]}, {"class_str": "book", "score": 0.422, "class_no": 74, "box_coords": [0.039, 0.337, 0.123, 0.37]}, {"class_str": "book", "score": 0.33, "class_no": 74, "box_coords": [0.009, 0.278, 0.117, 0.355]}, {"class_str": "book", "score": 0.279, "class_no": 74, "box_coords": [0.006, 0.267, 0.138, 0.402]}, {"class_str": "book", "score": 0.544, "class_no": 74, "box_coords": [0.053, 0.31, 0.11, 0.332]}, {"class_str": "book", "score": 0.06, "class_no": 74, "box_coords": [0.003, 0.291, 0.068, 0.341]}, {"class_str": "book", "score": 0.554, "class_no": 74, "box_coords": [0.031, 0.266, 0.103, 0.299]}, {"class_str": "book", "score": 0.12, "class_no": 74, "box_coords": [0.012, 0.264, 0.112, 0.323]}, {"class_str": "book", "score": 0.16, "class_no": 74, "box_coords": [0.039, 0.31, 0.13, 0.397]}, {"class_str": "book", "score": 0.054, "class_no": 74, "box_coords": [0.302, 0.009, 0.393, 0.054]}, {"class_str": "book", "score": 0.058, "class_no": 74, "box_coords": [0.028, 0.266, 0.068, 0.298]}, {"class_str": "book", "score": 0.263, "class_no": 74, "box_coords": [0.05, 0.374, 0.136, 0.402]}, {"class_str": "book", "score": 0.14, "class_no": 74, "box_coords": [0.067, 0.269, 0.102, 0.3]}, {"class_str": "book", "score": 0.177, "class_no": 74, "box_coords": [0.0, 0.28, 0.035, 0.341]}, {"class_str": "book", "score": 0.125, "class_no": 74, "box_coords": [0.084, 0.344, 0.12, 0.356]}, {"class_str": "book", "score": 0.087, "class_no": 74, "box_coords": [0.038, 0.294, 0.109, 0.319]}, {"class_str": "book", "score": 0.08, "class_no": 74, "box_coords": [0.06, 0.277, 0.106, 0.321]}], "image_name": "COCO_train2014_000000413489.jpg", "W": 640}