{"H": 569, "detections": [{"class_str": "person", "score": 0.999, "class_no": 1, "box_coords": [0.248, 0.274, 0.945, 0.585]}, {"class_str": "person", "score": 0.077, "class_no": 1, "box_coords": [0.037, 0.526, 0.14, 0.583]}, {"class_str": "bench", "score": 0.426, "class_no": 14, "box_coords": [0.739, 0.098, 0.959, 0.529]}, {"class_str": "handbag", "score": 0.913, "class_no": 27, "box_coords": [0.599, 0.548, 0.794, 0.608]}, {"class_str": "handbag", "score": 0.222, "class_no": 27, "box_coords": [0.407, 0.338, 0.786, 0.594]}, {"class_str": "handbag", "score": 0.066, "class_no": 27, "box_coords": [0.623, 0.316, 0.795, 0.601]}, {"class_str": "wine glass", "score": 0.109, "class_no": 41, "box_coords": [0.081, 0.896, 0.175, 0.94]}, {"class_str": "dining table", "score": 0.064, "class_no": 61, "box_coords": [0.745, 0.097, 0.961, 0.526]}, {"class_str": "cell phone", "score": 0.975, "class_no": 68, "box_coords": [0.341, 0.399, 0.396, 0.486]}, {"class_str": "cell phone", "score": 0.51, "class_no": 68, "box_coords": [0.353, 0.414, 0.393, 0.45]}], "image_name": "COCO_train2014_000000225530.jpg", "W": 640}