{"H": 640, "detections": [{"class_str": "person", "score": 0.999, "class_no": 1, "box_coords": [0.262, 0.164, 0.819, 0.591]}, {"class_str": "person", "score": 0.994, "class_no": 1, "box_coords": [0.264, 0.002, 0.741, 0.207]}, {"class_str": "person", "score": 0.239, "class_no": 1, "box_coords": [0.205, 0.278, 0.8, 0.774]}, {"class_str": "person", "score": 1.0, "class_no": 1, "box_coords": [0.137, 0.551, 0.768, 0.888]}, {"class_str": "person", "score": 0.601, "class_no": 1, "box_coords": [0.356, 0.083, 0.521, 0.217]}, {"class_str": "person", "score": 0.088, "class_no": 1, "box_coords": [0.273, 0.002, 0.615, 0.141]}, {"class_str": "person", "score": 0.053, "class_no": 1, "box_coords": [0.35, 0.081, 0.727, 0.315]}, {"class_str": "person", "score": 0.075, "class_no": 1, "box_coords": [0.358, 0.082, 0.457, 0.162]}, {"class_str": "person", "score": 0.062, "class_no": 1, "box_coords": [0.354, 0.064, 0.618, 0.183]}, {"class_str": "person", "score": 0.082, "class_no": 1, "box_coords": [0.275, 0.027, 0.778, 0.389]}, {"class_str": "frisbee", "score": 0.984, "class_no": 30, "box_coords": [0.153, 0.532, 0.174, 0.665]}, {"class_str": "frisbee", "score": 0.181, "class_no": 30, "box_coords": [0.155, 0.628, 0.17, 0.662]}, {"class_str": "baseball bat", "score": 0.072, "class_no": 35, "box_coords": [0.255, 0.181, 0.377, 0.227]}, {"class_str": "baseball bat", "score": 0.08, "class_no": 35, "box_coords": [0.252, 0.177, 0.476, 0.233]}], "image_name": "COCO_train2014_000000272479.jpg", "W": 428}