{"H": 360, "detections": [{"class_str": "person", "score": 1.0, "class_no": 1, "box_coords": [0.617, 0.726, 0.856, 0.828]}, {"class_str": "person", "score": 1.0, "class_no": 1, "box_coords": [0.562, 0.641, 0.823, 0.726]}, {"class_str": "person", "score": 0.95, "class_no": 1, "box_coords": [0.334, 0.071, 0.378, 0.08]}, {"class_str": "person", "score": 0.05, "class_no": 1, "box_coords": [0.338, 0.077, 0.378, 0.085]}, {"class_str": "person", "score": 0.872, "class_no": 1, "box_coords": [0.324, 0.037, 0.359, 0.05]}, {"class_str": "person", "score": 0.141, "class_no": 1, "box_coords": [0.322, 0.039, 0.338, 0.049]}, {"class_str": "person", "score": 0.085, "class_no": 1, "box_coords": [0.331, 0.067, 0.376, 0.077]}, {"class_str": "person", "score": 0.319, "class_no": 1, "box_coords": [0.34, 0.081, 0.378, 0.089]}, {"class_str": "person", "score": 0.062, "class_no": 1, "box_coords": [0.329, 0.042, 0.361, 0.052]}, {"class_str": "person", "score": 0.091, "class_no": 1, "box_coords": [0.343, 0.083, 0.364, 0.09]}, {"class_str": "bicycle", "score": 0.344, "class_no": 2, "box_coords": [0.339, 0.037, 0.365, 0.049]}, {"class_str": "car", "score": 0.995, "class_no": 3, "box_coords": [0.409, 0.001, 0.537, 0.062]}, {"class_str": "car", "score": 0.751, "class_no": 3, "box_coords": [0.353, 0.116, 0.391, 0.132]}, {"class_str": "motorcycle", "score": 0.561, "class_no": 4, "box_coords": [0.337, 0.037, 0.364, 0.05]}, {"class_str": "motorcycle", "score": 0.052, "class_no": 4, "box_coords": [0.35, 0.037, 0.364, 0.05]}, {"class_str": "bench", "score": 0.083, "class_no": 14, "box_coords": [0.396, 0.111, 0.416, 0.132]}, {"class_str": "horse", "score": 0.998, "class_no": 18, "box_coords": [0.637, 0.209, 0.989, 0.411]}, {"class_str": "horse", "score": 0.092, "class_no": 18, "box_coords": [0.566, 0.218, 0.654, 0.241]}, {"class_str": "horse", "score": 0.996, "class_no": 18, "box_coords": [0.463, 0.109, 0.649, 0.243]}, {"class_str": "skis", "score": 0.073, "class_no": 31, "box_coords": [0.828, 0.768, 0.866, 0.803]}, {"class_str": "snowboard", "score": 0.058, "class_no": 32, "box_coords": [0.828, 0.768, 0.866, 0.802]}, {"class_str": "skateboard", "score": 0.587, "class_no": 37, "box_coords": [0.827, 0.768, 0.866, 0.803]}, {"class_str": "surfboard", "score": 0.261, "class_no": 38, "box_coords": [0.83, 0.768, 0.868, 0.804]}, {"class_str": "potted plant", "score": 0.064, "class_no": 59, "box_coords": [0.351, 0.076, 0.428, 0.111]}], "image_name": "COCO_train2014_000000507580.jpg", "W": 640}