{"H": 640, "detections": [{"class_str": "person", "score": 1.0, "class_no": 1, "box_coords": [0.093, 0.309, 0.586, 0.535]}, {"class_str": "person", "score": 0.981, "class_no": 1, "box_coords": [0.005, 0.004, 0.172, 0.084]}, {"class_str": "person", "score": 0.701, "class_no": 1, "box_coords": [0.002, 0.875, 0.029, 0.889]}, {"class_str": "car", "score": 0.132, "class_no": 3, "box_coords": [0.009, 0.17, 0.153, 0.602]}, {"class_str": "car", "score": 0.368, "class_no": 3, "box_coords": [0.035, 0.171, 0.063, 0.275]}, {"class_str": "car", "score": 0.978, "class_no": 3, "box_coords": [0.015, 0.875, 0.063, 0.997]}, {"class_str": "car", "score": 0.052, "class_no": 3, "box_coords": [0.018, 0.726, 0.08, 0.835]}, {"class_str": "car", "score": 0.056, "class_no": 3, "box_coords": [0.011, 0.252, 0.104, 0.579]}, {"class_str": "car", "score": 0.709, "class_no": 3, "box_coords": [0.006, 0.278, 0.061, 0.481]}, {"class_str": "car", "score": 0.097, "class_no": 3, "box_coords": [0.032, 0.219, 0.06, 0.282]}, {"class_str": "car", "score": 0.269, "class_no": 3, "box_coords": [0.008, 0.595, 0.09, 0.84]}, {"class_str": "truck", "score": 0.97, "class_no": 8, "box_coords": [0.015, 0.11, 0.17, 0.606]}, {"class_str": "truck", "score": 0.478, "class_no": 8, "box_coords": [0.035, 0.171, 0.064, 0.277]}, {"class_str": "truck", "score": 0.208, "class_no": 8, "box_coords": [0.01, 0.131, 0.097, 0.611]}, {"class_str": "truck", "score": 0.897, "class_no": 8, "box_coords": [0.01, 0.594, 0.091, 0.834]}, {"class_str": "truck", "score": 0.596, "class_no": 8, "box_coords": [0.006, 0.278, 0.061, 0.474]}, {"class_str": "truck", "score": 0.138, "class_no": 8, "box_coords": [0.017, 0.878, 0.065, 0.997]}, {"class_str": "suitcase", "score": 0.996, "class_no": 29, "box_coords": [0.421, 0.178, 0.793, 0.435]}, {"class_str": "suitcase", "score": 0.998, "class_no": 29, "box_coords": [0.41, 0.424, 0.786, 0.7]}, {"class_str": "suitcase", "score": 0.739, "class_no": 29, "box_coords": [0.412, 0.248, 0.797, 0.651]}, {"class_str": "baseball bat", "score": 0.595, "class_no": 35, "box_coords": [0.031, 0.105, 0.059, 0.169]}], "image_name": "COCO_train2014_000000132137.jpg", "W": 480}