{"H": 428, "detections": [{"class_str": "person", "score": 0.998, "class_no": 1, "box_coords": [0.282, 0.203, 0.979, 0.674]}, {"class_str": "baseball glove", "score": 0.966, "class_no": 36, "box_coords": [0.085, 0.676, 0.243, 0.763]}, {"class_str": "bottle", "score": 0.985, "class_no": 40, "box_coords": [0.959, 0.581, 0.979, 0.649]}, {"class_str": "potted plant", "score": 0.128, "class_no": 59, "box_coords": [0.653, 0.077, 0.953, 0.25]}, {"class_str": "potted plant", "score": 0.111, "class_no": 59, "box_coords": [0.618, 0.134, 0.972, 0.397]}, {"class_str": "potted plant", "score": 0.551, "class_no": 59, "box_coords": [0.288, 0.145, 0.637, 0.289]}], "image_name": "COCO_train2014_000000020414.jpg", "W": 640}