{"H": 640, "detections": [{"class_str": "person", "score": 0.999, "class_no": 1, "box_coords": [0.206, 0.016, 0.966, 0.583]}, {"class_str": "person", "score": 0.065, "class_no": 1, "box_coords": [0.237, 0.158, 0.679, 0.567]}, {"class_str": "train", "score": 0.062, "class_no": 7, "box_coords": [0.129, 0.434, 0.561, 0.927]}, {"class_str": "train", "score": 0.104, "class_no": 7, "box_coords": [0.108, 0.015, 0.553, 0.999]}, {"class_str": "truck", "score": 0.272, "class_no": 8, "box_coords": [0.172, 0.032, 0.581, 0.999]}, {"class_str": "truck", "score": 0.067, "class_no": 8, "box_coords": [0.134, 0.432, 0.574, 0.933]}, {"class_str": "boat", "score": 0.14, "class_no": 9, "box_coords": [0.119, 0.29, 0.558, 0.963]}, {"class_str": "traffic light", "score": 0.95, "class_no": 10, "box_coords": [0.195, 0.488, 0.542, 0.87]}, {"class_str": "traffic light", "score": 0.053, "class_no": 10, "box_coords": [0.196, 0.528, 0.339, 0.698]}, {"class_str": "traffic light", "score": 0.993, "class_no": 10, "box_coords": [0.253, 0.005, 0.496, 0.221]}, {"class_str": "traffic light", "score": 0.051, "class_no": 10, "box_coords": [0.237, 0.55, 0.391, 0.713]}, {"class_str": "traffic light", "score": 0.055, "class_no": 10, "box_coords": [0.23, 0.0, 0.302, 0.102]}, {"class_str": "traffic light", "score": 0.151, "class_no": 10, "box_coords": [0.263, 0.574, 0.46, 0.755]}, {"class_str": "cat", "score": 0.081, "class_no": 16, "box_coords": [0.858, 0.477, 0.912, 0.581]}, {"class_str": "frisbee", "score": 0.186, "class_no": 30, "box_coords": [0.53, 0.873, 0.583, 0.998]}, {"class_str": "snowboard", "score": 0.262, "class_no": 32, "box_coords": [0.198, 0.218, 0.286, 0.646]}, {"class_str": "kite", "score": 0.052, "class_no": 34, "box_coords": [0.144, 0.417, 0.561, 0.958]}, {"class_str": "surfboard", "score": 0.061, "class_no": 38, "box_coords": [0.2, 0.215, 0.287, 0.652]}, {"class_str": "surfboard", "score": 0.053, "class_no": 38, "box_coords": [0.184, 0.173, 0.345, 0.646]}, {"class_str": "chair", "score": 0.062, "class_no": 57, "box_coords": [0.075, 0.907, 0.242, 0.998]}, {"class_str": "cell phone", "score": 0.064, "class_no": 68, "box_coords": [0.521, 0.479, 0.542, 0.494]}, {"class_str": "toothbrush", "score": 0.105, "class_no": 80, "box_coords": [0.528, 0.868, 0.582, 0.999]}], "image_name": "COCO_train2014_000000431893.jpg", "W": 480}