{"H": 480, "detections": [{"class_str": "person", "score": 0.999, "class_no": 1, "box_coords": [0.477, 0.149, 0.819, 0.235]}, {"class_str": "person", "score": 0.956, "class_no": 1, "box_coords": [0.451, 0.026, 0.518, 0.044]}, {"class_str": "person", "score": 0.931, "class_no": 1, "box_coords": [0.437, 0.715, 0.517, 0.735]}, {"class_str": "person", "score": 0.995, "class_no": 1, "box_coords": [0.44, 0.877, 0.512, 0.902]}, {"class_str": "person", "score": 0.855, "class_no": 1, "box_coords": [0.448, 0.629, 0.523, 0.649]}, {"class_str": "person", "score": 0.908, "class_no": 1, "box_coords": [0.432, 0.767, 0.521, 0.79]}, {"class_str": "person", "score": 0.944, "class_no": 1, "box_coords": [0.419, 0.532, 0.53, 0.554]}, {"class_str": "person", "score": 0.703, "class_no": 1, "box_coords": [0.451, 0.301, 0.495, 0.316]}, {"class_str": "person", "score": 0.636, "class_no": 1, "box_coords": [0.443, 0.615, 0.521, 0.63]}, {"class_str": "person", "score": 0.75, "class_no": 1, "box_coords": [0.435, 0.167, 0.476, 0.183]}, {"class_str": "person", "score": 0.642, "class_no": 1, "box_coords": [0.417, 0.493, 0.488, 0.512]}, {"class_str": "person", "score": 0.869, "class_no": 1, "box_coords": [0.437, 0.577, 0.531, 0.605]}, {"class_str": "person", "score": 0.561, "class_no": 1, "box_coords": [0.446, 0.377, 0.493, 0.393]}, {"class_str": "person", "score": 0.136, "class_no": 1, "box_coords": [0.453, 0.384, 0.491, 0.397]}, {"class_str": "person", "score": 0.685, "class_no": 1, "box_coords": [0.441, 0.178, 0.474, 0.19]}, {"class_str": "person", "score": 0.988, "class_no": 1, "box_coords": [0.432, 0.935, 0.515, 0.961]}, {"class_str": "person", "score": 0.149, "class_no": 1, "box_coords": [0.451, 0.653, 0.476, 0.665]}, {"class_str": "person", "score": 0.316, "class_no": 1, "box_coords": [0.46, 0.483, 0.486, 0.493]}, {"class_str": "person", "score": 0.999, "class_no": 1, "box_coords": [0.473, 0.45, 0.749, 0.577]}, {"class_str": "person", "score": 0.159, "class_no": 1, "box_coords": [0.446, 0.506, 0.495, 0.529]}, {"class_str": "person", "score": 0.07, "class_no": 1, "box_coords": [0.483, 0.332, 0.494, 0.341]}, {"class_str": "person", "score": 0.254, "class_no": 1, "box_coords": [0.452, 0.458, 0.489, 0.471]}, {"class_str": "person", "score": 0.248, "class_no": 1, "box_coords": [0.456, 0.39, 0.49, 0.399]}, {"class_str": "person", "score": 0.062, "class_no": 1, "box_coords": [0.443, 0.634, 0.471, 0.648]}, {"class_str": "person", "score": 0.387, "class_no": 1, "box_coords": [0.466, 0.352, 0.493, 0.365]}, {"class_str": "person", "score": 0.182, "class_no": 1, "box_coords": [0.469, 0.522, 0.527, 0.539]}, {"class_str": "person", "score": 0.174, "class_no": 1, "box_coords": [0.441, 0.639, 0.472, 0.656]}, {"class_str": "person", "score": 0.133, "class_no": 1, "box_coords": [0.446, 0.296, 0.477, 0.313]}, {"class_str": "person", "score": 0.152, "class_no": 1, "box_coords": [0.44, 0.245, 0.466, 0.257]}, {"class_str": "person", "score": 0.639, "class_no": 1, "box_coords": [0.447, 0.425, 0.491, 0.443]}, {"class_str": "person", "score": 0.109, "class_no": 1, "box_coords": [0.445, 0.63, 0.478, 0.645]}, {"class_str": "person", "score": 0.067, "class_no": 1, "box_coords": [0.42, 0.532, 0.479, 0.552]}, {"class_str": "person", "score": 0.984, "class_no": 1, "box_coords": [0.402, 0.785, 0.52, 0.827]}, {"class_str": "person", "score": 0.069, "class_no": 1, "box_coords": [0.432, 0.607, 0.526, 0.629]}, {"class_str": "person", "score": 0.058, "class_no": 1, "box_coords": [0.441, 0.615, 0.525, 0.645]}, {"class_str": "car", "score": 0.937, "class_no": 3, "box_coords": [0.389, 0.929, 0.421, 0.976]}, {"class_str": "car", "score": 0.369, "class_no": 3, "box_coords": [0.395, 0.567, 0.433, 0.635]}, {"class_str": "car", "score": 0.815, "class_no": 3, "box_coords": [0.436, 0.124, 0.476, 0.164]}, {"class_str": "car", "score": 0.941, "class_no": 3, "box_coords": [0.388, 0.844, 0.424, 0.927]}, {"class_str": "car", "score": 0.895, "class_no": 3, "box_coords": [0.435, 0.125, 0.475, 0.217]}, {"class_str": "car", "score": 0.845, "class_no": 3, "box_coords": [0.41, 0.507, 0.445, 0.587]}, {"class_str": "car", "score": 0.695, "class_no": 3, "box_coords": [0.429, 0.089, 0.454, 0.118]}, {"class_str": "car", "score": 0.584, "class_no": 3, "box_coords": [0.395, 0.649, 0.432, 0.734]}, {"class_str": "car", "score": 0.431, "class_no": 3, "box_coords": [0.442, 0.176, 0.472, 0.222]}, {"class_str": "car", "score": 0.601, "class_no": 3, "box_coords": [0.386, 0.97, 0.422, 0.998]}, {"class_str": "car", "score": 0.977, "class_no": 3, "box_coords": [0.447, 0.002, 0.485, 0.094]}, {"class_str": "car", "score": 0.569, "class_no": 3, "box_coords": [0.395, 0.645, 0.432, 0.673]}, {"class_str": "car", "score": 0.231, "class_no": 3, "box_coords": [0.45, 0.0, 0.486, 0.034]}, {"class_str": "car", "score": 0.099, "class_no": 3, "box_coords": [0.405, 0.713, 0.428, 0.737]}, {"class_str": "car", "score": 0.065, "class_no": 3, "box_coords": [0.391, 0.961, 0.421, 0.983]}, {"class_str": "car", "score": 0.357, "class_no": 3, "box_coords": [0.389, 0.948, 0.422, 0.994]}, {"class_str": "car", "score": 0.505, "class_no": 3, "box_coords": [0.423, 0.27, 0.464, 0.333]}, {"class_str": "car", "score": 0.172, "class_no": 3, "box_coords": [0.382, 0.979, 0.409, 0.999]}, {"class_str": "car", "score": 0.129, "class_no": 3, "box_coords": [0.411, 0.511, 0.463, 0.565]}, {"class_str": "car", "score": 0.072, "class_no": 3, "box_coords": [0.396, 0.512, 0.442, 0.72]}, {"class_str": "truck", "score": 0.058, "class_no": 8, "box_coords": [0.434, 0.125, 0.475, 0.219]}, {"class_str": "truck", "score": 0.155, "class_no": 8, "box_coords": [0.428, 0.088, 0.455, 0.118]}, {"class_str": "truck", "score": 0.083, "class_no": 8, "box_coords": [0.384, 0.97, 0.422, 0.998]}, {"class_str": "truck", "score": 0.059, "class_no": 8, "box_coords": [0.449, 0.0, 0.486, 0.097]}, {"class_str": "truck", "score": 0.121, "class_no": 8, "box_coords": [0.405, 0.511, 0.445, 0.613]}, {"class_str": "truck", "score": 0.053, "class_no": 8, "box_coords": [0.387, 0.931, 0.422, 0.985]}, {"class_str": "truck", "score": 0.804, "class_no": 8, "box_coords": [0.396, 0.566, 0.437, 0.647]}, {"class_str": "truck", "score": 0.399, "class_no": 8, "box_coords": [0.422, 0.259, 0.466, 0.338]}, {"class_str": "truck", "score": 0.431, "class_no": 8, "box_coords": [0.396, 0.651, 0.434, 0.733]}, {"class_str": "truck", "score": 0.064, "class_no": 8, "box_coords": [0.359, 0.72, 0.421, 0.777]}, {"class_str": "truck", "score": 0.197, "class_no": 8, "box_coords": [0.387, 0.838, 0.424, 0.928]}, {"class_str": "truck", "score": 0.128, "class_no": 8, "box_coords": [0.396, 0.51, 0.442, 0.727]}, {"class_str": "bird", "score": 0.12, "class_no": 15, "box_coords": [0.484, 0.331, 0.494, 0.341]}, {"class_str": "backpack", "score": 0.274, "class_no": 25, "box_coords": [0.504, 0.451, 0.516, 0.48]}, {"class_str": "handbag", "score": 0.096, "class_no": 27, "box_coords": [0.468, 0.631, 0.507, 0.646]}, {"class_str": "sports ball", "score": 0.997, "class_no": 33, "box_coords": [0.702, 0.676, 0.738, 0.706]}, {"class_str": "sports ball", "score": 0.998, "class_no": 33, "box_coords": [0.768, 0.293, 0.813, 0.329]}, {"class_str": "baseball glove", "score": 0.147, "class_no": 36, "box_coords": [0.554, 0.536, 0.57, 0.548]}], "image_name": "COCO_train2014_000000389048.jpg", "W": 640}