{"H": 478, "detections": [{"class_str": "person", "score": 0.999, "class_no": 1, "box_coords": [0.0, 0.589, 0.433, 0.969]}, {"class_str": "person", "score": 0.158, "class_no": 1, "box_coords": [0.376, 0.012, 0.953, 0.566]}, {"class_str": "person", "score": 0.761, "class_no": 1, "box_coords": [0.592, 0.0, 0.844, 0.202]}, {"class_str": "person", "score": 0.925, "class_no": 1, "box_coords": [0.103, 0.804, 0.311, 0.858]}, {"class_str": "person", "score": 0.069, "class_no": 1, "box_coords": [0.005, 0.341, 0.585, 0.93]}, {"class_str": "person", "score": 0.492, "class_no": 1, "box_coords": [0.595, 0.0, 0.96, 0.388]}, {"class_str": "person", "score": 0.997, "class_no": 1, "box_coords": [0.036, 0.075, 0.715, 0.639]}, {"class_str": "person", "score": 0.07, "class_no": 1, "box_coords": [0.599, 0.753, 0.902, 0.869]}, {"class_str": "person", "score": 0.058, "class_no": 1, "box_coords": [0.574, 0.2, 0.975, 0.489]}, {"class_str": "bird", "score": 0.059, "class_no": 15, "box_coords": [0.656, 0.748, 0.927, 0.826]}, {"class_str": "bird", "score": 0.256, "class_no": 15, "box_coords": [0.598, 0.752, 0.902, 0.869]}, {"class_str": "bird", "score": 0.55, "class_no": 15, "box_coords": [0.669, 0.648, 0.922, 0.742]}, {"class_str": "bottle", "score": 0.345, "class_no": 40, "box_coords": [0.281, 0.586, 0.34, 0.615]}, {"class_str": "bottle", "score": 0.059, "class_no": 40, "box_coords": [0.652, 0.657, 0.916, 0.736]}, {"class_str": "wine glass", "score": 0.987, "class_no": 41, "box_coords": [0.527, 0.274, 0.908, 0.43]}, {"class_str": "wine glass", "score": 0.975, "class_no": 41, "box_coords": [0.297, 0.798, 0.439, 0.843]}, {"class_str": "wine glass", "score": 0.982, "class_no": 41, "box_coords": [0.628, 0.173, 0.995, 0.382]}, {"class_str": "cup", "score": 0.064, "class_no": 42, "box_coords": [0.285, 0.586, 0.338, 0.615]}, {"class_str": "cup", "score": 0.083, "class_no": 42, "box_coords": [0.561, 0.754, 0.912, 0.869]}, {"class_str": "cup", "score": 0.066, "class_no": 42, "box_coords": [0.324, 0.921, 0.45, 0.984]}, {"class_str": "cup", "score": 0.058, "class_no": 42, "box_coords": [0.584, 0.271, 0.89, 0.397]}, {"class_str": "cup", "score": 0.986, "class_no": 42, "box_coords": [0.345, 0.943, 0.469, 0.989]}, {"class_str": "cup", "score": 0.175, "class_no": 42, "box_coords": [0.728, 0.55, 0.934, 0.626]}, {"class_str": "knife", "score": 0.056, "class_no": 44, "box_coords": [0.717, 0.424, 0.752, 0.567]}, {"class_str": "chair", "score": 0.225, "class_no": 57, "box_coords": [0.312, 0.003, 0.628, 0.104]}, {"class_str": "chair", "score": 0.063, "class_no": 57, "box_coords": [0.33, 0.05, 0.659, 0.123]}, {"class_str": "chair", "score": 0.369, "class_no": 57, "box_coords": [0.318, 0.047, 0.347, 0.103]}, {"class_str": "chair", "score": 0.226, "class_no": 57, "box_coords": [0.309, 0.908, 0.406, 0.986]}, {"class_str": "chair", "score": 0.066, "class_no": 57, "box_coords": [0.276, 0.839, 0.344, 0.856]}, {"class_str": "chair", "score": 0.188, "class_no": 57, "box_coords": [0.287, 0.095, 0.613, 0.531]}, {"class_str": "chair", "score": 0.054, "class_no": 57, "box_coords": [0.175, 0.876, 0.317, 0.911]}, {"class_str": "chair", "score": 0.144, "class_no": 57, "box_coords": [0.278, 0.367, 0.496, 0.559]}, {"class_str": "chair", "score": 0.494, "class_no": 57, "box_coords": [0.282, 0.36, 0.456, 0.458]}, {"class_str": "chair", "score": 0.103, "class_no": 57, "box_coords": [0.258, 0.827, 0.344, 0.872]}, {"class_str": "couch", "score": 0.505, "class_no": 58, "box_coords": [0.32, 0.003, 0.627, 0.103]}, {"class_str": "couch", "score": 0.303, "class_no": 58, "box_coords": [0.286, 0.0, 0.753, 0.593]}, {"class_str": "couch", "score": 0.076, "class_no": 58, "box_coords": [0.301, 0.0, 0.556, 0.52]}, {"class_str": "couch", "score": 0.057, "class_no": 58, "box_coords": [0.304, 0.0, 0.694, 0.165]}, {"class_str": "bed", "score": 0.061, "class_no": 60, "box_coords": [0.32, 0.003, 0.629, 0.102]}, {"class_str": "dining table", "score": 0.911, "class_no": 61, "box_coords": [0.393, 0.147, 0.962, 0.961]}, {"class_str": "dining table", "score": 0.524, "class_no": 61, "box_coords": [0.313, 0.403, 0.865, 0.997]}, {"class_str": "dining table", "score": 0.065, "class_no": 61, "box_coords": [0.599, 0.026, 0.999, 0.509]}, {"class_str": "dining table", "score": 0.383, "class_no": 61, "box_coords": [0.799, 0.025, 0.983, 0.466]}, {"class_str": "dining table", "score": 0.565, "class_no": 61, "box_coords": [0.677, 0.174, 0.991, 0.999]}, {"class_str": "dining table", "score": 0.108, "class_no": 61, "box_coords": [0.386, 0.034, 0.939, 0.581]}, {"class_str": "dining table", "score": 0.333, "class_no": 61, "box_coords": [0.827, 0.008, 0.991, 0.184]}, {"class_str": "dining table", "score": 0.11, "class_no": 61, "box_coords": [0.396, 0.462, 0.715, 0.818]}, {"class_str": "dining table", "score": 0.139, "class_no": 61, "box_coords": [0.802, 0.299, 0.985, 0.932]}, {"class_str": "dining table", "score": 0.06, "class_no": 61, "box_coords": [0.372, 0.515, 0.676, 0.998]}, {"class_str": "dining table", "score": 0.08, "class_no": 61, "box_coords": [0.326, 0.662, 0.971, 0.993]}, {"class_str": "laptop", "score": 0.983, "class_no": 64, "box_coords": [0.4, 0.437, 0.764, 0.817]}, {"class_str": "laptop", "score": 0.251, "class_no": 64, "box_coords": [0.452, 0.705, 0.513, 0.842]}, {"class_str": "laptop", "score": 0.362, "class_no": 64, "box_coords": [0.391, 0.703, 0.511, 0.881]}, {"class_str": "laptop", "score": 0.713, "class_no": 64, "box_coords": [0.429, 0.702, 0.505, 0.795]}, {"class_str": "laptop", "score": 0.094, "class_no": 64, "box_coords": [0.431, 0.697, 0.579, 0.809]}, {"class_str": "laptop", "score": 0.054, "class_no": 64, "box_coords": [0.477, 0.537, 0.761, 0.756]}, {"class_str": "laptop", "score": 0.055, "class_no": 64, "box_coords": [0.517, 0.325, 0.775, 0.715]}, {"class_str": "laptop", "score": 0.059, "class_no": 64, "box_coords": [0.548, 0.619, 0.616, 0.736]}, {"class_str": "laptop", "score": 0.081, "class_no": 64, "box_coords": [0.458, 0.789, 0.513, 0.85]}, {"class_str": "laptop", "score": 0.084, "class_no": 64, "box_coords": [0.415, 0.739, 0.537, 0.863]}, {"class_str": "laptop", "score": 0.06, "class_no": 64, "box_coords": [0.286, 0.389, 0.888, 0.885]}, {"class_str": "laptop", "score": 0.135, "class_no": 64, "box_coords": [0.334, 0.796, 0.509, 0.896]}, {"class_str": "laptop", "score": 0.057, "class_no": 64, "box_coords": [0.446, 0.639, 0.627, 0.814]}, {"class_str": "laptop", "score": 0.057, "class_no": 64, "box_coords": [0.414, 0.729, 0.534, 0.799]}, {"class_str": "mouse", "score": 0.215, "class_no": 65, "box_coords": [0.52, 0.868, 0.551, 0.903]}, {"class_str": "mouse", "score": 0.079, "class_no": 65, "box_coords": [0.685, 0.474, 0.721, 0.553]}, {"class_str": "remote", "score": 0.607, "class_no": 66, "box_coords": [0.284, 0.586, 0.339, 0.614]}, {"class_str": "keyboard", "score": 0.076, "class_no": 67, "box_coords": [0.612, 0.476, 0.735, 0.68]}, {"class_str": "keyboard", "score": 0.506, "class_no": 67, "box_coords": [0.598, 0.559, 0.738, 0.715]}, {"class_str": "keyboard", "score": 0.07, "class_no": 67, "box_coords": [0.437, 0.704, 0.503, 0.791]}, {"class_str": "cell phone", "score": 0.073, "class_no": 68, "box_coords": [0.52, 0.869, 0.551, 0.903]}, {"class_str": "cell phone", "score": 0.387, "class_no": 68, "box_coords": [0.467, 0.795, 0.51, 0.835]}, {"class_str": "book", "score": 0.051, "class_no": 74, "box_coords": [0.435, 0.701, 0.506, 0.793]}, {"class_str": "vase", "score": 0.631, "class_no": 76, "box_coords": [0.723, 0.552, 0.933, 0.625]}, {"class_str": "vase", "score": 0.441, "class_no": 76, "box_coords": [0.584, 0.751, 0.905, 0.874]}, {"class_str": "vase", "score": 0.352, "class_no": 76, "box_coords": [0.773, 0.745, 0.955, 0.815]}, {"class_str": "vase", "score": 0.317, "class_no": 76, "box_coords": [0.67, 0.653, 0.939, 0.736]}], "image_name": "COCO_train2014_000000477408.jpg", "W": 640}