{"H": 480, "detections": [{"class_str": "person", "score": 0.998, "class_no": 1, "box_coords": [0.544, 0.634, 0.764, 0.699]}, {"class_str": "person", "score": 0.996, "class_no": 1, "box_coords": [0.488, 0.555, 0.814, 0.633]}, {"class_str": "person", "score": 0.988, "class_no": 1, "box_coords": [0.587, 0.805, 0.731, 0.837]}, {"class_str": "person", "score": 0.998, "class_no": 1, "box_coords": [0.58, 0.361, 0.789, 0.424]}, {"class_str": "person", "score": 0.986, "class_no": 1, "box_coords": [0.612, 0.725, 0.74, 0.759]}, {"class_str": "person", "score": 0.776, "class_no": 1, "box_coords": [0.465, 0.945, 0.721, 0.997]}, {"class_str": "person", "score": 0.97, "class_no": 1, "box_coords": [0.603, 0.45, 0.767, 0.487]}, {"class_str": "person", "score": 0.667, "class_no": 1, "box_coords": [0.614, 0.338, 0.767, 0.379]}, {"class_str": "person", "score": 0.775, "class_no": 1, "box_coords": [0.585, 0.874, 0.719, 0.902]}, {"class_str": "person", "score": 0.285, "class_no": 1, "box_coords": [0.603, 0.442, 0.634, 0.455]}, {"class_str": "person", "score": 0.535, "class_no": 1, "box_coords": [0.635, 0.422, 0.706, 0.437]}, {"class_str": "person", "score": 0.839, "class_no": 1, "box_coords": [0.599, 0.439, 0.69, 0.458]}, {"class_str": "person", "score": 0.152, "class_no": 1, "box_coords": [0.541, 0.612, 0.712, 0.643]}, {"class_str": "person", "score": 0.228, "class_no": 1, "box_coords": [0.621, 0.349, 0.71, 0.373]}, {"class_str": "person", "score": 0.555, "class_no": 1, "box_coords": [0.587, 0.881, 0.662, 0.902]}, {"class_str": "person", "score": 0.344, "class_no": 1, "box_coords": [0.598, 0.452, 0.629, 0.464]}, {"class_str": "person", "score": 0.072, "class_no": 1, "box_coords": [0.599, 0.465, 0.623, 0.478]}, {"class_str": "person", "score": 0.135, "class_no": 1, "box_coords": [0.606, 0.423, 0.705, 0.446]}, {"class_str": "person", "score": 0.205, "class_no": 1, "box_coords": [0.666, 0.005, 0.695, 0.014]}, {"class_str": "person", "score": 0.138, "class_no": 1, "box_coords": [0.615, 0.861, 0.715, 0.878]}, {"class_str": "person", "score": 0.444, "class_no": 1, "box_coords": [0.434, 0.974, 0.772, 0.998]}, {"class_str": "person", "score": 0.598, "class_no": 1, "box_coords": [0.6, 0.483, 0.645, 0.499]}, {"class_str": "person", "score": 0.802, "class_no": 1, "box_coords": [0.578, 0.537, 0.788, 0.58]}, {"class_str": "person", "score": 0.073, "class_no": 1, "box_coords": [0.626, 0.869, 0.721, 0.89]}, {"class_str": "person", "score": 0.3, "class_no": 1, "box_coords": [0.597, 0.451, 0.656, 0.463]}, {"class_str": "person", "score": 0.13, "class_no": 1, "box_coords": [0.619, 0.432, 0.765, 0.504]}, {"class_str": "person", "score": 0.132, "class_no": 1, "box_coords": [0.644, 0.701, 0.718, 0.716]}, {"class_str": "person", "score": 0.085, "class_no": 1, "box_coords": [0.611, 0.697, 0.723, 0.737]}, {"class_str": "person", "score": 0.539, "class_no": 1, "box_coords": [0.543, 0.938, 0.72, 0.983]}, {"class_str": "person", "score": 0.328, "class_no": 1, "box_coords": [0.582, 0.859, 0.716, 0.89]}, {"class_str": "person", "score": 0.103, "class_no": 1, "box_coords": [0.512, 0.597, 0.794, 0.689]}, {"class_str": "person", "score": 0.233, "class_no": 1, "box_coords": [0.602, 0.45, 0.693, 0.48]}, {"class_str": "person", "score": 0.621, "class_no": 1, "box_coords": [0.593, 0.426, 0.701, 0.461]}, {"class_str": "person", "score": 0.264, "class_no": 1, "box_coords": [0.604, 0.319, 0.777, 0.407]}, {"class_str": "person", "score": 0.165, "class_no": 1, "box_coords": [0.589, 0.849, 0.722, 0.918]}, {"class_str": "person", "score": 0.094, "class_no": 1, "box_coords": [0.599, 0.703, 0.738, 0.769]}, {"class_str": "bench", "score": 0.071, "class_no": 14, "box_coords": [0.635, 0.258, 0.651, 0.31]}, {"class_str": "bench", "score": 0.2, "class_no": 14, "box_coords": [0.653, 0.233, 0.694, 0.348]}, {"class_str": "bench", "score": 0.144, "class_no": 14, "box_coords": [0.643, 0.26, 0.655, 0.308]}, {"class_str": "bench", "score": 0.421, "class_no": 14, "box_coords": [0.652, 0.219, 0.696, 0.288]}, {"class_str": "backpack", "score": 0.643, "class_no": 25, "box_coords": [0.598, 0.538, 0.673, 0.568]}, {"class_str": "backpack", "score": 0.263, "class_no": 25, "box_coords": [0.632, 0.349, 0.703, 0.373]}, {"class_str": "backpack", "score": 0.417, "class_no": 25, "box_coords": [0.533, 0.569, 0.664, 0.627]}, {"class_str": "backpack", "score": 0.06, "class_no": 25, "box_coords": [0.538, 0.604, 0.667, 0.64]}, {"class_str": "backpack", "score": 0.129, "class_no": 25, "box_coords": [0.61, 0.537, 0.681, 0.556]}, {"class_str": "backpack", "score": 0.159, "class_no": 25, "box_coords": [0.606, 0.549, 0.676, 0.575]}, {"class_str": "backpack", "score": 0.663, "class_no": 25, "box_coords": [0.544, 0.61, 0.62, 0.648]}, {"class_str": "backpack", "score": 0.874, "class_no": 25, "box_coords": [0.535, 0.588, 0.616, 0.644]}, {"class_str": "handbag", "score": 0.09, "class_no": 27, "box_coords": [0.635, 0.35, 0.705, 0.372]}, {"class_str": "skis", "score": 0.797, "class_no": 31, "box_coords": [0.777, 0.344, 0.794, 0.421]}, {"class_str": "skis", "score": 0.418, "class_no": 31, "box_coords": [0.728, 0.804, 0.749, 0.85]}, {"class_str": "skis", "score": 0.556, "class_no": 31, "box_coords": [0.798, 0.518, 0.812, 0.599]}, {"class_str": "skis", "score": 0.884, "class_no": 31, "box_coords": [0.748, 0.624, 0.774, 0.695]}, {"class_str": "skis", "score": 0.085, "class_no": 31, "box_coords": [0.722, 0.809, 0.736, 0.87]}, {"class_str": "skis", "score": 0.332, "class_no": 31, "box_coords": [0.756, 0.447, 0.77, 0.517]}, {"class_str": "skis", "score": 0.051, "class_no": 31, "box_coords": [0.586, 0.879, 0.727, 0.907]}, {"class_str": "skis", "score": 0.113, "class_no": 31, "box_coords": [0.774, 0.532, 0.809, 0.63]}, {"class_str": "skis", "score": 0.095, "class_no": 31, "box_coords": [0.748, 0.598, 0.789, 0.693]}, {"class_str": "skis", "score": 0.249, "class_no": 31, "box_coords": [0.789, 0.544, 0.806, 0.619]}, {"class_str": "skis", "score": 0.697, "class_no": 31, "box_coords": [0.791, 0.518, 0.814, 0.622]}, {"class_str": "skis", "score": 0.229, "class_no": 31, "box_coords": [0.765, 0.331, 0.795, 0.428]}, {"class_str": "skis", "score": 0.372, "class_no": 31, "box_coords": [0.58, 0.892, 0.723, 0.923]}, {"class_str": "skis", "score": 0.161, "class_no": 31, "box_coords": [0.734, 0.804, 0.749, 0.818]}, {"class_str": "skis", "score": 0.075, "class_no": 31, "box_coords": [0.741, 0.622, 0.762, 0.697]}, {"class_str": "skis", "score": 0.122, "class_no": 31, "box_coords": [0.776, 0.306, 0.787, 0.422]}, {"class_str": "skis", "score": 0.078, "class_no": 31, "box_coords": [0.722, 0.85, 0.737, 0.867]}, {"class_str": "skis", "score": 0.074, "class_no": 31, "box_coords": [0.717, 0.838, 0.733, 0.906]}, {"class_str": "skis", "score": 0.054, "class_no": 31, "box_coords": [0.796, 0.576, 0.812, 0.596]}, {"class_str": "skis", "score": 0.067, "class_no": 31, "box_coords": [0.717, 0.819, 0.729, 0.883]}, {"class_str": "skis", "score": 0.065, "class_no": 31, "box_coords": [0.722, 0.855, 0.735, 0.871]}, {"class_str": "skis", "score": 0.052, "class_no": 31, "box_coords": [0.749, 0.64, 0.771, 0.679]}, {"class_str": "skis", "score": 0.066, "class_no": 31, "box_coords": [0.763, 0.518, 0.775, 0.646]}, {"class_str": "skis", "score": 0.133, "class_no": 31, "box_coords": [0.719, 0.803, 0.747, 0.875]}, {"class_str": "skis", "score": 0.063, "class_no": 31, "box_coords": [0.796, 0.561, 0.813, 0.619]}, {"class_str": "skis", "score": 0.105, "class_no": 31, "box_coords": [0.639, 0.423, 0.762, 0.516]}, {"class_str": "skis", "score": 0.056, "class_no": 31, "box_coords": [0.781, 0.322, 0.803, 0.566]}, {"class_str": "skis", "score": 0.094, "class_no": 31, "box_coords": [0.605, 0.903, 0.714, 0.941]}, {"class_str": "skis", "score": 0.083, "class_no": 31, "box_coords": [0.771, 0.278, 0.805, 0.63]}, {"class_str": "skis", "score": 0.15, "class_no": 31, "box_coords": [0.59, 0.864, 0.721, 0.949]}, {"class_str": "snowboard", "score": 0.072, "class_no": 32, "box_coords": [0.727, 0.804, 0.747, 0.854]}, {"class_str": "snowboard", "score": 0.113, "class_no": 32, "box_coords": [0.695, 0.416, 0.754, 0.512]}, {"class_str": "snowboard", "score": 0.054, "class_no": 32, "box_coords": [0.734, 0.804, 0.749, 0.818]}, {"class_str": "snowboard", "score": 0.171, "class_no": 32, "box_coords": [0.643, 0.469, 0.744, 0.506]}, {"class_str": "snowboard", "score": 0.051, "class_no": 32, "box_coords": [0.64, 0.478, 0.681, 0.507]}, {"class_str": "snowboard", "score": 0.055, "class_no": 32, "box_coords": [0.628, 0.422, 0.738, 0.468]}, {"class_str": "snowboard", "score": 0.871, "class_no": 32, "box_coords": [0.641, 0.431, 0.746, 0.505]}, {"class_str": "snowboard", "score": 0.083, "class_no": 32, "box_coords": [0.704, 0.483, 0.743, 0.506]}, {"class_str": "snowboard", "score": 0.057, "class_no": 32, "box_coords": [0.78, 0.345, 0.794, 0.423]}, {"class_str": "snowboard", "score": 0.177, "class_no": 32, "box_coords": [0.697, 0.423, 0.745, 0.459]}, {"class_str": "snowboard", "score": 0.437, "class_no": 32, "box_coords": [0.679, 0.423, 0.753, 0.479]}, {"class_str": "snowboard", "score": 0.063, "class_no": 32, "box_coords": [0.698, 0.339, 0.753, 0.448]}, {"class_str": "surfboard", "score": 0.172, "class_no": 38, "box_coords": [0.542, 0.976, 0.829, 0.999]}], "image_name": "COCO_train2014_000000244132.jpg", "W": 640}