{"H": 481, "detections": [{"class_str": "person", "score": 0.998, "class_no": 1, "box_coords": [0.378, 0.28, 0.764, 0.534]}, {"class_str": "person", "score": 0.99, "class_no": 1, "box_coords": [0.314, 0.002, 0.489, 0.131]}, {"class_str": "person", "score": 0.974, "class_no": 1, "box_coords": [0.415, 0.597, 0.598, 0.678]}, {"class_str": "person", "score": 0.861, "class_no": 1, "box_coords": [0.304, 0.267, 0.358, 0.323]}, {"class_str": "person", "score": 0.574, "class_no": 1, "box_coords": [0.397, 0.525, 0.745, 0.662]}, {"class_str": "person", "score": 0.831, "class_no": 1, "box_coords": [0.369, 0.312, 0.486, 0.359]}, {"class_str": "person", "score": 0.094, "class_no": 1, "box_coords": [0.47, 0.516, 0.724, 0.616]}, {"class_str": "person", "score": 0.466, "class_no": 1, "box_coords": [0.351, 0.158, 0.405, 0.204]}, {"class_str": "person", "score": 0.082, "class_no": 1, "box_coords": [0.356, 0.106, 0.469, 0.199]}, {"class_str": "person", "score": 0.138, "class_no": 1, "box_coords": [0.365, 0.292, 0.553, 0.363]}, {"class_str": "traffic light", "score": 0.092, "class_no": 10, "box_coords": [0.25, 0.271, 0.28, 0.296]}, {"class_str": "bottle", "score": 0.238, "class_no": 40, "box_coords": [0.541, 0.652, 0.609, 0.674]}, {"class_str": "bottle", "score": 0.539, "class_no": 40, "box_coords": [0.468, 0.143, 0.529, 0.158]}, {"class_str": "bottle", "score": 0.106, "class_no": 40, "box_coords": [0.237, 0.04, 0.27, 0.049]}, {"class_str": "bottle", "score": 0.352, "class_no": 40, "box_coords": [0.446, 0.172, 0.511, 0.193]}, {"class_str": "bottle", "score": 0.096, "class_no": 40, "box_coords": [0.236, 0.033, 0.267, 0.04]}, {"class_str": "bottle", "score": 0.232, "class_no": 40, "box_coords": [0.437, 0.192, 0.511, 0.214]}, {"class_str": "bottle", "score": 0.071, "class_no": 40, "box_coords": [0.278, 0.034, 0.31, 0.043]}, {"class_str": "bottle", "score": 0.133, "class_no": 40, "box_coords": [0.281, 0.038, 0.311, 0.047]}, {"class_str": "bottle", "score": 0.061, "class_no": 40, "box_coords": [0.464, 0.149, 0.526, 0.164]}, {"class_str": "bottle", "score": 0.069, "class_no": 40, "box_coords": [0.234, 0.031, 0.266, 0.038]}, {"class_str": "bottle", "score": 0.101, "class_no": 40, "box_coords": [0.278, 0.03, 0.308, 0.039]}, {"class_str": "bottle", "score": 0.073, "class_no": 40, "box_coords": [0.283, 0.045, 0.312, 0.054]}, {"class_str": "bottle", "score": 0.104, "class_no": 40, "box_coords": [0.242, 0.049, 0.274, 0.058]}, {"class_str": "bottle", "score": 0.092, "class_no": 40, "box_coords": [0.283, 0.05, 0.312, 0.058]}, {"class_str": "bottle", "score": 0.15, "class_no": 40, "box_coords": [0.238, 0.036, 0.269, 0.043]}, {"class_str": "bottle", "score": 0.059, "class_no": 40, "box_coords": [0.242, 0.056, 0.272, 0.062]}, {"class_str": "wine glass", "score": 0.405, "class_no": 41, "box_coords": [0.771, 0.648, 0.857, 0.668]}, {"class_str": "wine glass", "score": 0.222, "class_no": 41, "box_coords": [0.758, 0.641, 0.858, 0.681]}, {"class_str": "cup", "score": 0.992, "class_no": 42, "box_coords": [0.626, 0.354, 0.697, 0.409]}, {"class_str": "cup", "score": 0.344, "class_no": 42, "box_coords": [0.482, 0.064, 0.515, 0.089]}, {"class_str": "cup", "score": 0.346, "class_no": 42, "box_coords": [0.457, 0.193, 0.513, 0.216]}, {"class_str": "cup", "score": 0.128, "class_no": 42, "box_coords": [0.488, 0.022, 0.512, 0.042]}, {"class_str": "fork", "score": 0.098, "class_no": 43, "box_coords": [0.737, 0.381, 0.752, 0.41]}, {"class_str": "knife", "score": 0.166, "class_no": 44, "box_coords": [0.683, 0.349, 0.744, 0.377]}, {"class_str": "knife", "score": 0.064, "class_no": 44, "box_coords": [0.84, 0.316, 0.847, 0.334]}, {"class_str": "knife", "score": 0.068, "class_no": 44, "box_coords": [0.737, 0.382, 0.751, 0.41]}, {"class_str": "spoon", "score": 0.13, "class_no": 45, "box_coords": [0.74, 0.379, 0.758, 0.41]}, {"class_str": "spoon", "score": 0.062, "class_no": 45, "box_coords": [0.887, 0.263, 0.908, 0.33]}, {"class_str": "bowl", "score": 0.092, "class_no": 46, "box_coords": [0.521, 0.005, 0.536, 0.066]}, {"class_str": "bowl", "score": 0.059, "class_no": 46, "box_coords": [0.86, 0.34, 0.961, 0.466]}, {"class_str": "bowl", "score": 0.93, "class_no": 46, "box_coords": [0.746, 0.328, 0.791, 0.406]}, {"class_str": "sandwich", "score": 0.118, "class_no": 49, "box_coords": [0.761, 0.413, 0.815, 0.469]}, {"class_str": "sandwich", "score": 0.292, "class_no": 49, "box_coords": [0.865, 0.352, 0.952, 0.461]}, {"class_str": "sandwich", "score": 0.28, "class_no": 49, "box_coords": [0.786, 0.306, 0.848, 0.389]}, {"class_str": "pizza", "score": 0.183, "class_no": 54, "box_coords": [0.784, 0.306, 0.848, 0.393]}, {"class_str": "pizza", "score": 0.216, "class_no": 54, "box_coords": [0.862, 0.353, 0.95, 0.46]}, {"class_str": "donut", "score": 0.084, "class_no": 55, "box_coords": [0.786, 0.31, 0.847, 0.387]}, {"class_str": "donut", "score": 0.678, "class_no": 55, "box_coords": [0.771, 0.462, 0.817, 0.514]}, {"class_str": "donut", "score": 0.298, "class_no": 55, "box_coords": [0.762, 0.415, 0.813, 0.468]}, {"class_str": "donut", "score": 0.082, "class_no": 55, "box_coords": [0.862, 0.354, 0.954, 0.459]}, {"class_str": "cake", "score": 0.116, "class_no": 56, "box_coords": [0.761, 0.415, 0.813, 0.47]}, {"class_str": "cake", "score": 0.522, "class_no": 56, "box_coords": [0.786, 0.31, 0.847, 0.389]}, {"class_str": "cake", "score": 0.494, "class_no": 56, "box_coords": [0.861, 0.358, 0.953, 0.459]}, {"class_str": "cake", "score": 0.333, "class_no": 56, "box_coords": [0.77, 0.459, 0.818, 0.514]}, {"class_str": "chair", "score": 0.062, "class_no": 57, "box_coords": [0.404, 0.177, 0.43, 0.233]}, {"class_str": "chair", "score": 0.4, "class_no": 57, "box_coords": [0.623, 0.579, 0.778, 0.748]}, {"class_str": "chair", "score": 0.752, "class_no": 57, "box_coords": [0.631, 0.573, 0.74, 0.697]}, {"class_str": "chair", "score": 0.174, "class_no": 57, "box_coords": [0.63, 0.588, 0.695, 0.692]}, {"class_str": "chair", "score": 0.104, "class_no": 57, "box_coords": [0.548, 0.575, 0.722, 0.693]}, {"class_str": "chair", "score": 0.073, "class_no": 57, "box_coords": [0.696, 0.554, 0.738, 0.582]}, {"class_str": "chair", "score": 0.109, "class_no": 57, "box_coords": [0.621, 0.607, 0.666, 0.699]}, {"class_str": "chair", "score": 0.095, "class_no": 57, "box_coords": [0.386, 0.104, 0.466, 0.174]}, {"class_str": "potted plant", "score": 0.807, "class_no": 59, "box_coords": [0.222, 0.558, 0.364, 0.623]}, {"class_str": "potted plant", "score": 0.112, "class_no": 59, "box_coords": [0.619, 0.584, 0.787, 0.753]}, {"class_str": "potted plant", "score": 0.625, "class_no": 59, "box_coords": [0.59, 0.648, 0.866, 0.748]}, {"class_str": "potted plant", "score": 0.066, "class_no": 59, "box_coords": [0.506, 0.647, 0.612, 0.68]}, {"class_str": "dining table", "score": 0.067, "class_no": 61, "box_coords": [0.408, 0.222, 0.426, 0.294]}, {"class_str": "dining table", "score": 0.45, "class_no": 61, "box_coords": [0.582, 0.528, 0.714, 0.705]}, {"class_str": "dining table", "score": 0.227, "class_no": 61, "box_coords": [0.561, 0.515, 0.653, 0.72]}, {"class_str": "dining table", "score": 0.092, "class_no": 61, "box_coords": [0.414, 0.194, 0.428, 0.288]}, {"class_str": "dining table", "score": 0.209, "class_no": 61, "box_coords": [0.406, 0.189, 0.435, 0.302]}, {"class_str": "dining table", "score": 0.131, "class_no": 61, "box_coords": [0.422, 0.013, 0.582, 0.328]}, {"class_str": "dining table", "score": 0.119, "class_no": 61, "box_coords": [0.493, 0.0, 0.56, 0.279]}, {"class_str": "dining table", "score": 0.064, "class_no": 61, "box_coords": [0.719, 0.236, 0.921, 0.914]}, {"class_str": "dining table", "score": 0.965, "class_no": 61, "box_coords": [0.71, 0.013, 0.992, 0.996]}, {"class_str": "dining table", "score": 0.185, "class_no": 61, "box_coords": [0.6, 0.517, 0.643, 0.691]}, {"class_str": "dining table", "score": 0.079, "class_no": 61, "box_coords": [0.555, 0.272, 0.998, 0.934]}, {"class_str": "tv", "score": 0.118, "class_no": 63, "box_coords": [0.383, 0.524, 0.591, 0.656]}, {"class_str": "tv", "score": 0.428, "class_no": 63, "box_coords": [0.385, 0.101, 0.469, 0.173]}, {"class_str": "tv", "score": 0.875, "class_no": 63, "box_coords": [0.372, 0.522, 0.53, 0.617]}, {"class_str": "laptop", "score": 0.996, "class_no": 64, "box_coords": [0.519, 0.528, 0.606, 0.623]}, {"class_str": "laptop", "score": 0.059, "class_no": 64, "box_coords": [0.408, 0.245, 0.422, 0.291]}, {"class_str": "laptop", "score": 0.135, "class_no": 64, "box_coords": [0.397, 0.518, 0.597, 0.627]}, {"class_str": "laptop", "score": 0.487, "class_no": 64, "box_coords": [0.383, 0.1, 0.471, 0.167]}, {"class_str": "cell phone", "score": 0.776, "class_no": 68, "box_coords": [0.464, 0.626, 0.489, 0.642]}, {"class_str": "cell phone", "score": 0.139, "class_no": 68, "box_coords": [0.46, 0.629, 0.474, 0.641]}, {"class_str": "cell phone", "score": 0.406, "class_no": 68, "box_coords": [0.463, 0.623, 0.482, 0.637]}, {"class_str": "cell phone", "score": 0.077, "class_no": 68, "box_coords": [0.463, 0.62, 0.483, 0.631]}, {"class_str": "cell phone", "score": 0.377, "class_no": 68, "box_coords": [0.463, 0.632, 0.477, 0.644]}, {"class_str": "cell phone", "score": 0.112, "class_no": 68, "box_coords": [0.465, 0.618, 0.481, 0.627]}, {"class_str": "cell phone", "score": 0.327, "class_no": 68, "box_coords": [0.449, 0.622, 0.493, 0.644]}, {"class_str": "book", "score": 0.064, "class_no": 74, "box_coords": [0.485, 0.091, 0.513, 0.142]}, {"class_str": "book", "score": 0.106, "class_no": 74, "box_coords": [0.486, 0.114, 0.51, 0.143]}, {"class_str": "clock", "score": 0.094, "class_no": 75, "box_coords": [0.212, 0.21, 0.293, 0.251]}, {"class_str": "vase", "score": 0.522, "class_no": 76, "box_coords": [0.544, 0.651, 0.611, 0.676]}, {"class_str": "vase", "score": 0.092, "class_no": 76, "box_coords": [0.452, 0.191, 0.512, 0.214]}, {"class_str": "vase", "score": 0.335, "class_no": 76, "box_coords": [0.325, 0.595, 0.362, 0.608]}, {"class_str": "vase", "score": 0.064, "class_no": 76, "box_coords": [0.653, 0.643, 0.867, 0.74]}, {"class_str": "vase", "score": 0.997, "class_no": 76, "box_coords": [0.708, 0.684, 0.872, 0.742]}], "image_name": "COCO_train2014_000000510859.jpg", "W": 640}