{"H": 425, "detections": [{"class_str": "person", "score": 0.998, "class_no": 1, "box_coords": [0.335, 0.821, 0.989, 0.999]}, {"class_str": "person", "score": 1.0, "class_no": 1, "box_coords": [0.305, 0.23, 0.992, 0.628]}, {"class_str": "person", "score": 0.952, "class_no": 1, "box_coords": [0.561, 0.541, 0.813, 0.617]}, {"class_str": "person", "score": 0.557, "class_no": 1, "box_coords": [0.447, 0.0, 0.956, 0.101]}, {"class_str": "person", "score": 0.126, "class_no": 1, "box_coords": [0.473, 0.402, 0.979, 0.619]}, {"class_str": "person", "score": 0.052, "class_no": 1, "box_coords": [0.56, 0.535, 0.683, 0.598]}, {"class_str": "person", "score": 0.339, "class_no": 1, "box_coords": [0.546, 0.525, 0.981, 0.628]}, {"class_str": "person", "score": 0.082, "class_no": 1, "box_coords": [0.559, 0.535, 0.637, 0.578]}, {"class_str": "bus", "score": 0.116, "class_no": 6, "box_coords": [0.157, 0.0, 0.992, 0.135]}, {"class_str": "bus", "score": 0.191, "class_no": 6, "box_coords": [0.007, 0.072, 0.999, 0.925]}, {"class_str": "bus", "score": 0.107, "class_no": 6, "box_coords": [0.0, 0.015, 0.999, 0.275]}, {"class_str": "backpack", "score": 0.156, "class_no": 25, "box_coords": [0.599, 0.333, 0.994, 0.556]}, {"class_str": "umbrella", "score": 0.053, "class_no": 26, "box_coords": [0.296, 0.761, 0.676, 0.833]}, {"class_str": "tie", "score": 0.998, "class_no": 28, "box_coords": [0.61, 0.392, 0.985, 0.541]}, {"class_str": "bottle", "score": 0.069, "class_no": 40, "box_coords": [0.492, 0.001, 0.994, 0.104]}, {"class_str": "tv", "score": 0.077, "class_no": 63, "box_coords": [0.496, 0.0, 0.999, 0.107]}, {"class_str": "cell phone", "score": 0.988, "class_no": 68, "box_coords": [0.478, 0.324, 0.559, 0.37]}, {"class_str": "cell phone", "score": 0.301, "class_no": 68, "box_coords": [0.473, 0.327, 0.648, 0.415]}], "image_name": "COCO_train2014_000000501299.jpg", "W": 640}